landusemix/__init__.py
landusemix/indices.py
landusemix/utils.py
landusemix/data/raster.tif
landusemix/data/sample.csv
landusemix/data/geojson/half.geojson
landusemix/data/geojson/multiple.geojson
landusemix/data/geojson/one.geojson
landusemix/data/shapefiles/half.cpg
landusemix/data/shapefiles/half.dbf
landusemix/data/shapefiles/half.prj
landusemix/data/shapefiles/half.qix
landusemix/data/shapefiles/half.qmd
landusemix/data/shapefiles/half.shp
landusemix/data/shapefiles/half.shx
landusemix/data/shapefiles/multiple.cpg
landusemix/data/shapefiles/multiple.dbf
landusemix/data/shapefiles/multiple.prj
landusemix/data/shapefiles/multiple.qix
landusemix/data/shapefiles/multiple.shp
landusemix/data/shapefiles/multiple.shx
landusemix/data/shapefiles/one.dbf
landusemix/data/shapefiles/one.prj
landusemix/data/shapefiles/one.qmd
landusemix/data/shapefiles/one.shp
landusemix/data/shapefiles/one.shx
tests/__init__.py
tests/test_landusemix.py
landusemix-0.1.3.dist-info/LICENSE
landusemix-0.1.3.dist-info/METADATA
landusemix-0.1.3.dist-info/WHEEL
landusemix-0.1.3.dist-info/top_level.txt
landusemix-0.1.3.dist-info/RECORD
