Metadata-Version: 2.1
Name: landusemix
Version: 0.1.3
Summary: A package for calculating land use mix indices
Home-page: https://github.com/makyol/landusemix
Author: Mehmet Ali Akyol
Author-email: akyol.mehmet@metu.edu.tr
Classifier: Programming Language :: Python :: 3
Classifier: License :: OSI Approved :: MIT License
Classifier: Operating System :: OS Independent
Requires-Python: >=3.6
License-File: LICENSE
Requires-Dist: pandas
Requires-Dist: geopandas
Requires-Dist: rasterio
